odoo/addons/mrp_warehouse_calendar/README.rst
odoo/addons/mrp_warehouse_calendar/__init__.py
odoo/addons/mrp_warehouse_calendar/__manifest__.py
odoo/addons/mrp_warehouse_calendar/i18n/de.po
odoo/addons/mrp_warehouse_calendar/i18n/mrp_warehouse_calendar.pot
odoo/addons/mrp_warehouse_calendar/i18n/pt_BR.po
odoo/addons/mrp_warehouse_calendar/models/__init__.py
odoo/addons/mrp_warehouse_calendar/models/mrp_production.py
odoo/addons/mrp_warehouse_calendar/models/stock_rule.py
odoo/addons/mrp_warehouse_calendar/readme/CONFIGURE.rst
odoo/addons/mrp_warehouse_calendar/readme/CONTRIBUTORS.rst
odoo/addons/mrp_warehouse_calendar/readme/DESCRIPTION.rst
odoo/addons/mrp_warehouse_calendar/readme/USAGE.rst
odoo/addons/mrp_warehouse_calendar/static/description/icon.png
odoo/addons/mrp_warehouse_calendar/static/description/index.html
odoo/addons/mrp_warehouse_calendar/tests/__init__.py
odoo/addons/mrp_warehouse_calendar/tests/test_mrp_warehouse_calendar.py
odoo12_addon_mrp_warehouse_calendar-12.0.1.0.2.dist-info/METADATA
odoo12_addon_mrp_warehouse_calendar-12.0.1.0.2.dist-info/WHEEL
odoo12_addon_mrp_warehouse_calendar-12.0.1.0.2.dist-info/top_level.txt
odoo12_addon_mrp_warehouse_calendar-12.0.1.0.2.dist-info/RECORD
